sage_stream/__init__.py
sage_stream/admin.py
sage_stream/apps.py
sage_stream/models.py
sage_stream/settings.py
sage_stream/api/__init__.py
sage_stream/api/urls.py
sage_stream/api/views.py
sage_stream/migrations/__init__.py
sage_stream/utils/__init__.py
sage_stream/utils/file_services.py
sage_stream/utils/log_services.py
sage_stream/utils/stream_services.py
fork_django_streaming-0.2.0.dist-info/AUTHORS.md
fork_django_streaming-0.2.0.dist-info/LICENSE
fork_django_streaming-0.2.0.dist-info/METADATA
fork_django_streaming-0.2.0.dist-info/WHEEL
fork_django_streaming-0.2.0.dist-info/top_level.txt
fork_django_streaming-0.2.0.dist-info/RECORD
